.gitignore
00.create_env.bat
01.update_env.bat
02.remove_env.bat
README.md
__init__.py
enviroment.yml
setup.py
upload.bat
config/Install.bat
config/Install_geopandas.bat
config/Install_jupyter_spyder.bat
config/create_env.bat
config/requirements_geopandas.txt
config/start_jupyter.bat
config/start_spyder.bat
config/img_readme/crisp_process.jpg
config/img_readme/install.PNG
data_science_helper/__init__.py
data_science_helper/helper_batch_process.py
data_science_helper/helper_cache.py
data_science_helper/helper_classification_model.py
data_science_helper/helper_clean.py
data_science_helper/helper_clustering.py
data_science_helper/helper_dataframe.py
data_science_helper/helper_feature_selection.py
data_science_helper/helper_functions.py
data_science_helper/helper_general.py
data_science_helper/helper_output.py
data_science_helper/helper_plot.py
data_science_helper/helper_transformers.py
data_science_helper/model/__init__.py
data_science_helper/model/custom_bagging__lgb_model.py
data_science_helper/model/general.py
data_science_helper/model/lgb_model.py
data_science_helper/model/neg_bagging_fraction__lgb_model.py
data_science_helper/model/optuna.py
data_science_helper/model/scale_pos_weight__lgb_model.py
data_science_helper_utility.egg-info/PKG-INFO
data_science_helper_utility.egg-info/SOURCES.txt
data_science_helper_utility.egg-info/dependency_links.txt
data_science_helper_utility.egg-info/requires.txt
data_science_helper_utility.egg-info/top_level.txt
docs/docsPrincipal.md
docs/docdetalle/helpercache/HELPER_CACHE_get_cache.md
docs/docdetalle/helpercache/HELPER_CACHE_get_key_cache.md
docs/docdetalle/helpercache/HELPER_CACHE_save_cache.md
docs/docdetalle/helperclean/HELPER_CLEAN_agregar_na_cls.md
docs/docdetalle/helperclean/HELPER_CLEAN_fill_nan_with_mean_in_cl.md
docs/docdetalle/helperclean/HELPER_CLEAN_fill_nan_with_nan_category_in_cls.md
docs/docdetalle/helperclean/HELPER_CLEAN_trim_category_cls.md
docs/docdetalle/helperclean/HELPER_CLEAN_upper_category_cls.md
docs/docdetalle/helperdataframe/HELPER_DATAFRAME_Diff.md
docs/docdetalle/helperdataframe/HELPER_DATAFRAME_generate_dataset.md
docs/docdetalle/helperdataframe/HELPER_DATAFRAME_get_bool_columns.md
