Metadata-Version: 2.1
Name: data-science-helper-utility
Version: 0.0.112
Summary: data-science-helper de proyectos de analitica avanzada
Download-URL: https://URL_PAQUETE/data-science-helper-utility/-/archive/master/data-science-helper-utility-master.tar
Author: Analitica Avanzada
Author-email: analitica.avanzada.talento@gmail.com
License: NOTFOUND
Keywords: data-science-helper-utility,ds-helper,paquete,package
Classifier: Development Status :: 4 - Beta
Classifier: Intended Audience :: Developers
Classifier: Topic :: Software Development :: Build Tools
Classifier: Programming Language :: Python :: 3.7
Requires-Dist: pandas>=1.2.2
Requires-Dist: numpy>=1.19.2
Requires-Dist: matplotlib>=3.5.0
Requires-Dist: plotly>=5.5.0
Requires-Dist: seaborn==0.9.0
Requires-Dist: scikit-learn>=0.23.2
Requires-Dist: scikit-plot>=0.3.7
Requires-Dist: pyodbc>=4.0.30
Requires-Dist: missingno>=0.4.2
Requires-Dist: shap>=0.38.1
Requires-Dist: wordcloud>=1.6.0
Requires-Dist: lightgbm>=3.3.2
Requires-Dist: imbalanced-learn>=0.7.0
Requires-Dist: requests>=2.27.1
Requires-Dist: optuna>=2.4.0
